aio_ld2410/__init__.py
aio_ld2410/exceptions.py
aio_ld2410/ld2410.py
aio_ld2410/models.py
aio_ld2410/py.typed
aio_ld2410/stream.py
aio_ld2410/version.py
aio_ld2410/protocol/__init__.py
aio_ld2410/protocol/command.py
aio_ld2410/protocol/frame.py
aio_ld2410/protocol/report.py
aio_ld2410-1.0.2.dist-info/licenses/LICENSE
aio_ld2410-1.0.2.dist-info/METADATA
aio_ld2410-1.0.2.dist-info/WHEEL
aio_ld2410-1.0.2.dist-info/top_level.txt
aio_ld2410-1.0.2.dist-info/RECORD
