Metadata-Version: 2.4
Name: aio-ld2410
Version: 1.0.2
Summary: Asynchonous library for the HiLink LD2410 presence detector module
Author-email: Romain Bezut <morian@xdec.net>
Project-URL: Changelog, https://github.com/morian/aio-ld2410/blob/master/CHANGELOG.rst
Project-URL: Coverage, https://app.codecov.io/github/morian/aio-ld2410
Project-URL: Documentation, https://aio-ld2410.readthedocs.io
Project-URL: Homepage, https://pypi.org/project/aio-ld2410/
Project-URL: Issues, https://github.com/morian/aio-ld2410/issues
Project-URL: Repository, https://github.com/morian/aio-ld2410
Classifier: Framework :: AsyncIO
Classifier: Intended Audience :: Developers
Classifier: License :: OSI Approved :: MIT License
Classifier: Operating System :: POSIX :: Linux
Classifier: Programming Language :: Python :: 3
Classifier: Programming Language :: Python :: 3 :: Only
Classifier: Programming Language :: Python :: 3.9
Classifier: Programming Language :: Python :: 3.10
Classifier: Programming Language :: Python :: 3.11
Classifier: Programming Language :: Python :: 3.12
Classifier: Programming Language :: Python :: 3.13
Classifier: Programming Language :: Python :: 3.14
Classifier: Topic :: Home Automation
Classifier: Topic :: Scientific/Engineering :: Human Machine Interfaces
Classifier: Topic :: Software Development :: Embedded Systems
Classifier: Topic :: Software Development :: Libraries :: Python Modules
Classifier: Topic :: System :: Hardware
Classifier: Topic :: Terminals :: Serial
Classifier: Typing :: Typed
Requires-Python: >=3.9
License-File: LICENSE
Requires-Dist: async-timeout>=4; python_version < "3.11"
Requires-Dist: construct<3.0,>=2.10
Requires-Dist: dacite<2.0,>=1.8
Requires-Dist: pyserial-asyncio-fast<1.0,>=0.14
Dynamic: license-file
